{
  "generatedAt": "2026-07-06T21:30:27.242Z",
  "universe": "US",
  "scanned": 340,
  "count": 17,
  "strongCount": 0,
  "watchCount": 17,
  "officialFewAccount": 0,
  "watchlist": [
    {
      "ticker": "PETS",
      "name": "PetMed Express, Inc.",
      "tier": "watch",
      "score": 36,
      "coFire": 2,
      "lead": [
        "거래량 추세 21.3× 상승(지속 매집)",
        "거래량 56.7× 급증(가격 평탄)",
        "아래꼬리 매집 3개(저가 매수받침)"
      ],
      "runup20dPct": 7.7,
      "runup5dPct": 11.4,
      "medDollarVolUsd": 188032,
      "smartAccum": false,
      "official": null
    },
    {
      "ticker": "WSR",
      "name": "Whitestone REIT",
      "tier": "watch",
      "score": 34,
      "coFire": 2,
      "lead": [
        "거래량 추세 2.7× 상승(지속 매집)",
        "변동성 수축(coiling) — 돌파 압축",
        "아래꼬리 매집 5개(저가 매수받침)"
      ],
      "runup20dPct": -0.5,
      "runup5dPct": 0,
      "medDollarVolUsd": 7456968,
      "smartAccum": false,
      "official": null
    },
    {
      "ticker": "WSBF",
      "name": "Waterstone Financial, Inc.",
      "tier": "watch",
      "score": 34,
      "coFire": 2,
      "lead": [
        "거래량 추세 2.2× 상승(지속 매집)",
        "종가 일중 상단 70%(강한 매수 흡수)",
        "아래꼬리 매집 6개(저가 매수받침)"
      ],
      "runup20dPct": 7.4,
      "runup5dPct": -1.9,
      "medDollarVolUsd": 1099560,
      "smartAccum": false,
      "official": null
    },
    {
      "ticker": "ONL",
      "name": "Orion Properties Inc.",
      "tier": "watch",
      "score": 30,
      "coFire": 2,
      "lead": [
        "거래량 추세 3.1× 상승(지속 매집)",
        "종가 일중 상단 60%",
        "아래꼬리 매집 4개(저가 매수받침)"
      ],
      "runup20dPct": -2.7,
      "runup5dPct": -2.4,
      "medDollarVolUsd": 888848,
      "smartAccum": false,
      "official": null
    },
    {
      "ticker": "BMRC",
      "name": "Bank of Marin Bancorp",
      "tier": "watch",
      "score": 30,
      "coFire": 2,
      "lead": [
        "거래량 추세 2.5× 상승(지속 매집)",
        "종가 일중 상단 60%",
        "아래꼬리 매집 5개(저가 매수받침)"
      ],
      "runup20dPct": 10.6,
      "runup5dPct": 2.6,
      "medDollarVolUsd": 2713763,
      "smartAccum": false,
      "official": null
    },
    {
      "ticker": "CBL",
      "name": "CBL & Associates Properties, In",
      "tier": "watch",
      "score": 27,
      "coFire": 2,
      "lead": [
        "거래량 추세 1.8× 상승",
        "종가 일중 상단 70%(강한 매수 흡수)",
        "아래꼬리 매집 5개(저가 매수받침)"
      ],
      "runup20dPct": 11.3,
      "runup5dPct": -1,
      "medDollarVolUsd": 11218650,
      "smartAccum": false,
      "official": null
    },
    {
      "ticker": "HFWA",
      "name": "Heritage Financial Corporation",
      "tier": "watch",
      "score": 27,
      "coFire": 2,
      "lead": [
        "거래량 추세 1.5× 상승",
        "종가 일중 상단 70%(강한 매수 흡수)",
        "아래꼬리 매집 5개(저가 매수받침)"
      ],
      "runup20dPct": 7.9,
      "runup5dPct": 1,
      "medDollarVolUsd": 6756322,
      "smartAccum": false,
      "official": null
    },
    {
      "ticker": "BTT",
      "name": "BlackRock Municipal 2030 Target",
      "tier": "watch",
      "score": 26,
      "coFire": 2,
      "lead": [
        "거래량 추세 1.9× 상승",
        "흡수 매집봉 2개(대량거래·변동폭 억제)",
        "아래꼬리 매집 3개(저가 매수받침)"
      ],
      "runup20dPct": 0.7,
      "runup5dPct": 1.1,
      "medDollarVolUsd": 1730460,
      "smartAccum": false,
      "official": null
    },
    {
      "ticker": "MHF",
      "name": "Western Asset Municipal High In",
      "tier": "watch",
      "score": 25,
      "coFire": 2,
      "lead": [
        "거래량 추세 2.4× 상승(지속 매집)",
        "흡수 매집봉 2개(대량거래·변동폭 억제)"
      ],
      "runup20dPct": 2.3,
      "runup5dPct": 2.3,
      "medDollarVolUsd": 345114,
      "smartAccum": false,
      "official": null
    },
    {
      "ticker": "TWO",
      "name": "Two Harbors Investment Corp",
      "tier": "watch",
      "score": 23,
      "coFire": 2,
      "lead": [
        "거래량 추세 1.7× 상승",
        "종가 일중 상단 60%",
        "아래꼬리 매집 3개(저가 매수받침)"
      ],
      "runup20dPct": -2.2,
      "runup5dPct": -2.7,
      "medDollarVolUsd": 18946400,
      "smartAccum": false,
      "official": null
    },
    {
      "ticker": "PMT",
      "name": "PennyMac Mortgage Investment Tr",
      "tier": "watch",
      "score": 23,
      "coFire": 2,
      "lead": [
        "거래량 추세 1.9× 상승",
        "종가 일중 상단 60%",
        "아래꼬리 매집 5개(저가 매수받침)"
      ],
      "runup20dPct": 7,
      "runup5dPct": 1.2,
      "medDollarVolUsd": 12034386,
      "smartAccum": false,
      "official": null
    },
    {
      "ticker": "CBZ",
      "name": "CBIZ, Inc.",
      "tier": "watch",
      "score": 23,
      "coFire": 2,
      "lead": [
        "거래량 추세 1.6× 상승",
        "종가 일중 상단 60%",
        "아래꼬리 매집 3개(저가 매수받침)"
      ],
      "runup20dPct": 6,
      "runup5dPct": 12,
      "medDollarVolUsd": 21255321,
      "smartAccum": false,
      "official": null
    },
    {
      "ticker": "NRIM",
      "name": "Northrim BanCorp Inc",
      "tier": "watch",
      "score": 23,
      "coFire": 2,
      "lead": [
        "거래량 추세 1.8× 상승",
        "종가 일중 상단 60%",
        "아래꼬리 매집 4개(저가 매수받침)"
      ],
      "runup20dPct": 9.9,
      "runup5dPct": -2.5,
      "medDollarVolUsd": 2956160,
      "smartAccum": false,
      "official": null
    },
    {
      "ticker": "PGC",
      "name": "Peapack-Gladstone Financial Cor",
      "tier": "watch",
      "score": 23,
      "coFire": 2,
      "lead": [
        "거래량 추세 1.8× 상승",
        "종가 일중 상단 60%",
        "아래꼬리 매집 5개(저가 매수받침)"
      ],
      "runup20dPct": 9,
      "runup5dPct": -0.3,
      "medDollarVolUsd": 5337250,
      "smartAccum": false,
      "official": null
    },
    {
      "ticker": "THFF",
      "name": "First Financial Corporation",
      "tier": "watch",
      "score": 23,
      "coFire": 2,
      "lead": [
        "거래량 추세 1.9× 상승",
        "종가 일중 상단 60%",
        "아래꼬리 매집 4개(저가 매수받침)"
      ],
      "runup20dPct": 9,
      "runup5dPct": -0.8,
      "medDollarVolUsd": 6021939,
      "smartAccum": false,
      "official": null
    },
    {
      "ticker": "MCB",
      "name": "Metropolitan Bank Holding Corp.",
      "tier": "watch",
      "score": 23,
      "coFire": 2,
      "lead": [
        "거래량 추세 1.6× 상승",
        "종가 일중 상단 60%",
        "아래꼬리 매집 3개(저가 매수받침)"
      ],
      "runup20dPct": 10.9,
      "runup5dPct": 0.4,
      "medDollarVolUsd": 10847432,
      "smartAccum": false,
      "official": null
    },
    {
      "ticker": "OSUR",
      "name": "OraSure Technologies, Inc.",
      "tier": "watch",
      "score": 16,
      "coFire": 2,
      "lead": [
        "변동성 수축(coiling) — 돌파 압축",
        "종가 일중 상단 60%"
      ],
      "runup20dPct": 4.8,
      "runup5dPct": -2,
      "medDollarVolUsd": 2241392,
      "smartAccum": false,
      "official": null
    }
  ]
}
